sarmadtec_neuroport/__init__.py
sarmadtec_neuroport/device.py
sarmadtec_neuroport-0.2.0.dist-info/METADATA
sarmadtec_neuroport-0.2.0.dist-info/WHEEL
sarmadtec_neuroport-0.2.0.dist-info/top_level.txt
sarmadtec_neuroport-0.2.0.dist-info/RECORD
