Metadata-Version: 2.4
Name: sarmadtec-neuroport
Version: 0.2.0
Summary: Sarmadtec NeuroPort driver for Fascin8/Ultim8 neuro headstages with faker mode for offline testing.
Author: sarmadtec
License: Proprietary
Project-URL: Homepage, https://github.com/mosh/recorder
Project-URL: Source, https://github.com/mosh/recorder
Project-URL: Issues, https://github.com/mosh/recorder/issues
Keywords: EEG,neural,serial,driver,fascin8,ultim8
Classifier: Development Status :: 3 - Alpha
Classifier: Intended Audience :: Developers
Classifier: License :: Other/Proprietary License
Classifier: Programming Language :: Python
Classifier: Programming Language :: Python :: 3
Classifier: Programming Language :: Python :: 3 :: Only
Classifier: Topic :: Scientific/Engineering
Classifier: Topic :: System :: Hardware :: Hardware Drivers
Requires-Python: >=3.8
Requires-Dist: pyserial>=3.5
